koschey/__init__.py
koschey-0.1.1.dist-info/METADATA
koschey-0.1.1.dist-info/WHEEL
koschey-0.1.1.dist-info/entry_points.txt
koschey-0.1.1.dist-info/licenses/LICENSE
koschey-0.1.1.dist-info/RECORD
