Metadata-Version: 2.4
Name: koschey
Version: 0.1.1
Summary: Internal immortal PyPI index — a standards-compliant mirror and package host with quarantine, provenance (PEP 710), and JSON API (PEP 691).
Project-URL: Homepage, https://pypi.org/project/koschey/
Project-URL: Repository, https://github.com/alvassin/koschey
Project-URL: Issues, https://github.com/alvassin/koschey/issues
Author-email: Alexander Vasin <hi@alvass.in>
License: Apache License 2.0
License-File: LICENSE
Keywords: index,internal,kadex,koschey,mirror,packages,pypi
Classifier: Development Status :: 2 - Pre-Alpha
Classifier: Intended Audience :: Developers
Classifier: Intended Audience :: Information Technology
Classifier: Intended Audience :: System Administrators
Classifier: License :: OSI Approved :: Apache Software License
Classifier: Operating System :: MacOS
Classifier: Operating System :: POSIX
Classifier: Operating System :: POSIX :: BSD
Classifier: Operating System :: POSIX :: Linux
Classifier: Programming Language :: Python :: 3
Classifier: Programming Language :: Python :: 3.12
Classifier: Topic :: Software Development :: Build Tools
Classifier: Topic :: System :: Archiving :: Packaging
Classifier: Topic :: System :: Software Distribution
Requires-Python: >=3.12
